{"collection":"CoinDesk","entries":[{"feedUrl":"https://www.coindesk.com/arc/outboundfeeds/rss/","feedTitle":"CoinDesk","title":"Blockchain-Based Polymarket Eyes U.S. Comeback by November: BBG","link":"https://www.coindesk.com/markets/2025/10/28/blockchain-based-polymarket-eyes-u-s-comeback-by-november-bbg","author":"Helene Braun","rawPubDate":"Tue, 28 Oct 2025 19:40:57 +0000","timestamp":1761680457},{"feedUrl":"https://www.coindesk.com/arc/outboundfeeds/rss/","feedTitle":"CoinDesk","title":"Ethereum’s Fusaka Upgrade Completes Final Hoodi Test Ahead of Mainnet Launch","link":"https://www.coindesk.com/tech/2025/10/28/ethereum-s-fusaka-upgrade-completes-final-hoodi-test-ahead-of-mainnet-launch","author":"Margaux Nijkerk","rawPubDate":"Tue, 28 Oct 2025 19:14:45 +0000","timestamp":1761678885},{"feedUrl":"https://www.coindesk.com/arc/outboundfeeds/rss/","feedTitle":"CoinDesk","title":"SharpLink Plans $200M ETH Deployment on Consensys’ Linea Over Multiple Years","link":"https://www.coindesk.com/markets/2025/10/28/sharplink-plans-usd200m-eth-deployment-on-consensys-linea-over-multiple-years","author":"Siamak Masnavi","rawPubDate":"Tue, 28 Oct 2025 18:41:00 +0000","timestamp":1761676860},{"feedUrl":"https://www.coindesk.com/arc/outboundfeeds/rss/","feedTitle":"CoinDesk","title":"Chainlink Underpins Balcony's $240B Real Estate Tokenization Platform","link":"https://www.coindesk.com/markets/2025/10/28/chainlink-underpins-balcony-s-usd240b-real-estate-tokenization-platform","author":"CD Analytics","rawPubDate":"Tue, 28 Oct 2025 18:24:11 +0000","timestamp":1761675851},{"feedUrl":"https://www.coindesk.com/arc/outboundfeeds/rss/","feedTitle":"CoinDesk","title":"Western Union to Launch Stablecoin on Solana With Anchorage Digital","link":"https://www.coindesk.com/business/2025/10/28/western-union-to-launch-stablecoin-on-solana-with-anchorage-digital","author":"Krisztian Sandor","rawPubDate":"Tue, 28 Oct 2025 18:16:06 +0000","timestamp":1761675366},{"feedUrl":"https://www.coindesk.com/arc/outboundfeeds/rss/","feedTitle":"CoinDesk","title":"Bitcoin's Offshoot, BCH, Edges Up 1% to Challenge Downtrend","link":"https://www.coindesk.com/markets/2025/10/28/bitcoin-s-offshoot-bch-edges-up-1-16-to-usd56-challenges-dowtrend","author":"CD Analytics","rawPubDate":"Tue, 28 Oct 2025 18:01:58 +0000","timestamp":1761674518},{"feedUrl":"https://www.coindesk.com/arc/outboundfeeds/rss/","feedTitle":"CoinDesk","title":"55 Years of Financial Surveillance","link":"https://www.coindesk.com/opinion/2025/10/28/55-years-of-financial-surveillance","author":"Nicholas Anthony","rawPubDate":"Tue, 28 Oct 2025 18:00:00 +0000","timestamp":1761674400},{"feedUrl":"https://www.coindesk.com/arc/outboundfeeds/rss/","feedTitle":"CoinDesk","title":"Wealth Managers Scramble to Add Crypto as UAE's Ultra-Rich Demand Digital Assets","link":"https://www.coindesk.com/business/2025/10/28/wealth-managers-scramble-to-add-crypto-as-uae-s-ultra-rich-demand-digital-assets","author":"Ian Allison","rawPubDate":"Tue, 28 Oct 2025 17:07:28 +0000","timestamp":1761671248},{"feedUrl":"https://www.coindesk.com/arc/outboundfeeds/rss/","feedTitle":"CoinDesk","title":"Heather 'Razzlekhan' Morgan's Release From Prison Wasn't Us, White House Says ","link":"https://www.coindesk.com/policy/2025/10/28/heather-razzlekhan-morgan-s-release-from-prison-wasn-t-us-white-house-says","author":"Jesse Hamilton","rawPubDate":"Tue, 28 Oct 2025 16:50:06 +0000","timestamp":1761670206},{"feedUrl":"https://www.coindesk.com/arc/outboundfeeds/rss/","feedTitle":"CoinDesk","title":"XLM Gains 2.3% to $0.3314 as Payment Networks Drive Institutional Interest","link":"https://www.coindesk.com/markets/2025/10/28/xlm-gains-2-3-to-usd0-3314-as-payment-networks-drive-institutional-interest","author":"CD Analytics","rawPubDate":"Tue, 28 Oct 2025 16:31:15 +0000","timestamp":1761669075},{"feedUrl":"https://www.coindesk.com/arc/outboundfeeds/rss/","feedTitle":"CoinDesk","title":"BNB Drops After $1.65B Token Burn, Eyes Resistance Near $1,150","link":"https://www.coindesk.com/markets/2025/10/28/bnb-drops-after-usd1-65b-token-burn-eyes-resistance-near-usd1-150","author":"CD Analytics","rawPubDate":"Tue, 28 Oct 2025 16:27:38 +0000","timestamp":1761668858},{"feedUrl":"https://www.coindesk.com/arc/outboundfeeds/rss/","feedTitle":"CoinDesk","title":"Hedera Jumps 25.7% Breaking Key Resistance as Spot ETF Launches","link":"https://www.coindesk.com/markets/2025/10/28/hbar-surged-25-7-breaking-key-resistance-as-spot-etf-launches","author":"CD Analytics","rawPubDate":"Tue, 28 Oct 2025 16:10:13 +0000","timestamp":1761667813},{"feedUrl":"https://www.coindesk.com/arc/outboundfeeds/rss/","feedTitle":"CoinDesk","title":"ICP Hovers Around $3.20 Resistance With 115% Volume Surge","link":"https://www.coindesk.com/markets/2025/10/28/icp-hovers-around-usd3-20-resistance-with-115-volume-surge","author":"Jamie Crawley","rawPubDate":"Tue, 28 Oct 2025 16:02:38 +0000","timestamp":1761667358},{"feedUrl":"https://www.coindesk.com/arc/outboundfeeds/rss/","feedTitle":"CoinDesk","title":"Solana ETFs Could Draw Over $3B If Bitcoin, Ether ETF Trends Repeat","link":"https://www.coindesk.com/markets/2025/10/28/solana-etfs-could-draw-over-usd3b-if-bitcoin-ether-etf-trends-repeat","author":"Helene Braun","rawPubDate":"Tue, 28 Oct 2025 15:50:46 +0000","timestamp":1761666646},{"feedUrl":"https://www.coindesk.com/arc/outboundfeeds/rss/","feedTitle":"CoinDesk","title":"Bitcoin Miners Sit on Prime Power Assets as AI Pivot Accelerates: Canaccord","link":"https://www.coindesk.com/markets/2025/10/28/bitcoin-miners-sit-on-prime-power-assets-as-ai-pivot-accelerates-canaccord","author":"Will Canny","rawPubDate":"Tue, 28 Oct 2025 15:29:36 +0000","timestamp":1761665376},{"feedUrl":"https://www.coindesk.com/arc/outboundfeeds/rss/","feedTitle":"CoinDesk","title":"Crypto Backers for Trump's Ballroom Project Remain Largely in Shadows During Fallout ","link":"https://www.coindesk.com/policy/2025/10/28/crypto-backers-for-trump-s-ballroom-project-remain-largely-in-shadows-during-fallout","author":"Jesse Hamilton","rawPubDate":"Tue, 28 Oct 2025 15:26:35 +0000","timestamp":1761665195},{"feedUrl":"https://www.coindesk.com/arc/outboundfeeds/rss/","feedTitle":"CoinDesk","title":"BOB Unveils Bitcoin Vault Liquidation Engine to Power BTC-Backed Stablecoin Lending","link":"https://www.coindesk.com/tech/2025/10/28/bob-unveils-bitcoin-vault-liquidation-engine-to-power-btc-backed-stablecoin-lending","author":"Jamie Crawley","rawPubDate":"Tue, 28 Oct 2025 15:05:49 +0000","timestamp":1761663949},{"feedUrl":"https://www.coindesk.com/arc/outboundfeeds/rss/","feedTitle":"CoinDesk","title":"Ethena-Backed DEX Terminal Finance Reaches $280M in Pre-Launch Deposits","link":"https://www.coindesk.com/business/2025/10/27/ethena-backed-dex-terminal-finance-reaches-usd280m-in-pre-launch-deposits","author":"Oliver Knight","rawPubDate":"Tue, 28 Oct 2025 15:01:53 +0000","timestamp":1761663713},{"feedUrl":"https://www.coindesk.com/arc/outboundfeeds/rss/","feedTitle":"CoinDesk","title":"Shipping Firm OceanPal Adds AI Arm With $120M PIPE Deal, Eyes 10% of NEAR Supply","link":"https://www.coindesk.com/business/2025/10/28/shipping-firm-oceanpal-adds-ai-arm-with-usd120m-pipe-deal-eyes-10-of-near-supply","author":"Francisco Rodrigues","rawPubDate":"Tue, 28 Oct 2025 14:38:29 +0000","timestamp":1761662309},{"feedUrl":"https://www.coindesk.com/arc/outboundfeeds/rss/","feedTitle":"CoinDesk","title":"TeraWulf Stock Surges 22% After $9.5B Google-Backed AI Compute Deal With Fluidstack","link":"https://www.coindesk.com/business/2025/10/28/terawulf-stock-surges-22-after-usd9-5b-google-backed-ai-compute-deal-with-fluidstack","author":"Krisztian Sandor","rawPubDate":"Tue, 28 Oct 2025 14:21:03 +0000","timestamp":1761661263},{"feedUrl":"https://www.coindesk.com/arc/outboundfeeds/rss/","feedTitle":"CoinDesk","title":"Galaxy Digital Slips 7% on $1.15B Exchangeable Debt Raise","link":"https://www.coindesk.com/markets/2025/10/28/galaxy-digital-slips-7-on-usd1-15b-debt-raise","author":"James Van Straten","rawPubDate":"Tue, 28 Oct 2025 14:00:22 +0000","timestamp":1761660022},{"feedUrl":"https://www.coindesk.com/arc/outboundfeeds/rss/","feedTitle":"CoinDesk","title":"PEPE Holds Key Support Level as Volume Surge Points to Whale Trading Activity","link":"https://www.coindesk.com/markets/2025/10/28/pepe-holds-key-support-level-as-volume-surge-points-to-whale-trading-activity","author":"CD Analytics","rawPubDate":"Tue, 28 Oct 2025 13:43:10 +0000","timestamp":1761658990},{"feedUrl":"https://www.coindesk.com/arc/outboundfeeds/rss/","feedTitle":"CoinDesk","title":"Trump Media Taps Crypto.com to Launch Prediction Markets on Truth Social","link":"https://www.coindesk.com/markets/2025/10/28/trump-media-taps-crypto-com-to-launch-prediction-markets-on-truth-social","author":"Helene Braun","rawPubDate":"Tue, 28 Oct 2025 13:13:09 +0000","timestamp":1761657189},{"feedUrl":"https://www.coindesk.com/arc/outboundfeeds/rss/","feedTitle":"CoinDesk","title":"CoinDesk 20 Performance Update: Hedera (HBAR) Surges 14.4% While Index Trades Lower","link":"https://www.coindesk.com/coindesk-indices/2025/10/28/coindesk-20-performance-update-hedera-hbar-surges-14-4-while-index-trades-lower","author":"CoinDesk Indices","rawPubDate":"Tue, 28 Oct 2025 13:09:21 +0000","timestamp":1761656961},{"feedUrl":"https://www.coindesk.com/arc/outboundfeeds/rss/","feedTitle":"CoinDesk","title":"Bitcoin Treasury Firm Strive Adds 72 BTC to Treasury After Warrant Exercises","link":"https://www.coindesk.com/markets/2025/10/28/bitcoin-treasury-firm-strive-adds-72-btc-to-treasury-after-warrant-exercises","author":"James Van Straten","rawPubDate":"Tue, 28 Oct 2025 13:08:10 +0000","timestamp":1761656890}]}