{"collection":"阮一峰的网络日志","entries":[{"feedUrl":"https://www.ruanyifeng.com/blog/atom.xml","feedTitle":"阮一峰的网络日志","title":"科技爱好者周刊（第 338 期）：重新思考 6G","link":"http://www.ruanyifeng.com/blog/2025/02/weekly-issue-338.html","author":"阮一峰","rawPubDate":"2025-02-21T00:17:51.000Z","timestamp":1740097071},{"feedUrl":"https://www.ruanyifeng.com/blog/atom.xml","feedTitle":"阮一峰的网络日志","title":"科技爱好者周刊（第 337 期）：互联网创业几乎没了","link":"http://www.ruanyifeng.com/blog/2025/02/weekly-issue-337.html","author":"阮一峰","rawPubDate":"2025-02-14T00:15:27.000Z","timestamp":1739492127},{"feedUrl":"https://www.ruanyifeng.com/blog/atom.xml","feedTitle":"阮一峰的网络日志","title":"科技爱好者周刊（第 336 期）：面对 AI，互联网正在衰落","link":"http://www.ruanyifeng.com/blog/2025/02/weekly-issue-336.html","author":"阮一峰","rawPubDate":"2025-02-07T00:20:56.000Z","timestamp":1738887656}]}